biaswrappers/__init__.py
biaswrappers/baseline_tests.py
biaswrappers/regressor.py
biaswrappers-0.5.1.3.dist-info/LICENSE
biaswrappers-0.5.1.3.dist-info/METADATA
biaswrappers-0.5.1.3.dist-info/WHEEL
biaswrappers-0.5.1.3.dist-info/top_level.txt
biaswrappers-0.5.1.3.dist-info/RECORD
