Metadata-Version: 2.1
Name: biaswrappers
Version: 0.5.1.3
Summary: A set of Regression Wrappers that combats bias in data for machine learning models through custom regularization techniques.
Home-page: https://github.com/karthiksing05/biaswrappers
Author: Karthik Singaravadivelan
Author-email: Karthik Singaravadivelan <karthiksing05@gmail.com>
Classifier: License :: OSI Approved :: MIT License
Requires-Python: >=3.7
License-File: LICENSE
Requires-Dist: scikit-learn >=1.0
Requires-Dist: numpy >=1.21.6
